{
  "mockup": {
    "controls": {
      "control": [
        {
          "typeID": "Label",
          "x": 20,
          "y": 10,
          "measuredW": 200,
          "measuredH": 30,
          "properties": {
            "text": "Verification Engineer",
            "size": 28,
            "color": 1710638
          }
        },
        {
          "typeID": "Canvas",
          "x": 10,
          "y": 60,
          "measuredW": 780,
          "measuredH": 80,
          "properties": {
            "color": 16317180,
            "borderColor": 14870768,
            "backgroundAlpha": 0.5
          }
        },
        {
          "typeID": "TextInput",
          "x": 20,
          "y": 70,
          "measuredW": 760,
          "measuredH": 25,
          "properties": {
            "text": "Foundations",
            "size": 15,
            "bold": true,
            "color": 2848996,
            "borderColor": 2848996,
            "textColor": 16777215
          }
        },
        {
          "typeID": "__group__",
          "x": 20,
          "y": 100,
          "measuredW": 140,
          "measuredH": 30,
          "properties": {
            "controlName": "mindset@mindset"
          },
          "children": {
            "controls": {
              "control": [
                {
                  "typeID": "TextInput",
                  "x": 0,
                  "y": 0,
                  "measuredW": 140,
                  "measuredH": 30,
                  "properties": {
                    "text": "Mindset",
                    "size": 13,
                    "color": 16777215,
                    "borderColor": 2848996,
                    "backgroundAlpha": 1
                  }
                }
              ]
            }
          }
        },
        {
          "typeID": "__group__",
          "x": 170,
          "y": 100,
          "measuredW": 140,
          "measuredH": 30,
          "properties": {
            "controlName": "testbenches@testbenches"
          },
          "children": {
            "controls": {
              "control": [
                {
                  "typeID": "TextInput",
                  "x": 0,
                  "y": 0,
                  "measuredW": 140,
                  "measuredH": 30,
                  "properties": {
                    "text": "Testbenches",
                    "size": 13,
                    "color": 16777215,
                    "borderColor": 2848996,
                    "backgroundAlpha": 1
                  }
                }
              ]
            }
          }
        },
        {
          "typeID": "__group__",
          "x": 320,
          "y": 100,
          "measuredW": 140,
          "measuredH": 30,
          "properties": {
            "controlName": "simulation@simulation"
          },
          "children": {
            "controls": {
              "control": [
                {
                  "typeID": "TextInput",
                  "x": 0,
                  "y": 0,
                  "measuredW": 140,
                  "measuredH": 30,
                  "properties": {
                    "text": "Simulation",
                    "size": 13,
                    "color": 16777215,
                    "borderColor": 2848996,
                    "backgroundAlpha": 1
                  }
                }
              ]
            }
          }
        },
        {
          "typeID": "__group__",
          "x": 470,
          "y": 100,
          "measuredW": 140,
          "measuredH": 30,
          "properties": {
            "controlName": "bug-hunting@bug-hunting"
          },
          "children": {
            "controls": {
              "control": [
                {
                  "typeID": "TextInput",
                  "x": 0,
                  "y": 0,
                  "measuredW": 140,
                  "measuredH": 30,
                  "properties": {
                    "text": "Bug Hunting",
                    "size": 13,
                    "color": 16777215,
                    "borderColor": 2848996,
                    "backgroundAlpha": 1
                  }
                }
              ]
            }
          }
        },
        {
          "typeID": "Canvas",
          "x": 10,
          "y": 160,
          "measuredW": 780,
          "measuredH": 80,
          "properties": {
            "color": 16317180,
            "borderColor": 14870768,
            "backgroundAlpha": 0.5
          }
        },
        {
          "typeID": "TextInput",
          "x": 20,
          "y": 170,
          "measuredW": 760,
          "measuredH": 25,
          "properties": {
            "text": "SystemVerilog",
            "size": 15,
            "bold": true,
            "color": 5208616,
            "borderColor": 5208616,
            "textColor": 16777215
          }
        },
        {
          "typeID": "__group__",
          "x": 20,
          "y": 200,
          "measuredW": 140,
          "measuredH": 30,
          "properties": {
            "controlName": "oop@oop"
          },
          "children": {
            "controls": {
              "control": [
                {
                  "typeID": "TextInput",
                  "x": 0,
                  "y": 0,
                  "measuredW": 140,
                  "measuredH": 30,
                  "properties": {
                    "text": "OOP",
                    "size": 13,
                    "color": 16777215,
                    "borderColor": 5208616,
                    "backgroundAlpha": 1
                  }
                }
              ]
            }
          }
        },
        {
          "typeID": "__group__",
          "x": 170,
          "y": 200,
          "measuredW": 140,
          "measuredH": 30,
          "properties": {
            "controlName": "randomization@randomization"
          },
          "children": {
            "controls": {
              "control": [
                {
                  "typeID": "TextInput",
                  "x": 0,
                  "y": 0,
                  "measuredW": 140,
                  "measuredH": 30,
                  "properties": {
                    "text": "Randomization",
                    "size": 13,
                    "color": 16777215,
                    "borderColor": 5208616,
                    "backgroundAlpha": 1
                  }
                }
              ]
            }
          }
        },
        {
          "typeID": "__group__",
          "x": 320,
          "y": 200,
          "measuredW": 140,
          "measuredH": 30,
          "properties": {
            "controlName": "coverage@coverage"
          },
          "children": {
            "controls": {
              "control": [
                {
                  "typeID": "TextInput",
                  "x": 0,
                  "y": 0,
                  "measuredW": 140,
                  "measuredH": 30,
                  "properties": {
                    "text": "Coverage",
                    "size": 13,
                    "color": 16777215,
                    "borderColor": 5208616,
                    "backgroundAlpha": 1
                  }
                }
              ]
            }
          }
        },
        {
          "typeID": "__group__",
          "x": 470,
          "y": 200,
          "measuredW": 140,
          "measuredH": 30,
          "properties": {
            "controlName": "assertions@assertions"
          },
          "children": {
            "controls": {
              "control": [
                {
                  "typeID": "TextInput",
                  "x": 0,
                  "y": 0,
                  "measuredW": 140,
                  "measuredH": 30,
                  "properties": {
                    "text": "Assertions",
                    "size": 13,
                    "color": 16777215,
                    "borderColor": 5208616,
                    "backgroundAlpha": 1
                  }
                }
              ]
            }
          }
        },
        {
          "typeID": "Canvas",
          "x": 10,
          "y": 260,
          "measuredW": 780,
          "measuredH": 80,
          "properties": {
            "color": 16317180,
            "borderColor": 14870768,
            "backgroundAlpha": 0.5
          }
        },
        {
          "typeID": "TextInput",
          "x": 20,
          "y": 270,
          "measuredW": 760,
          "measuredH": 25,
          "properties": {
            "text": "UVM",
            "size": 15,
            "bold": true,
            "color": 8867582,
            "borderColor": 8867582,
            "textColor": 16777215
          }
        },
        {
          "typeID": "__group__",
          "x": 20,
          "y": 300,
          "measuredW": 140,
          "measuredH": 30,
          "properties": {
            "controlName": "architecture@architecture"
          },
          "children": {
            "controls": {
              "control": [
                {
                  "typeID": "TextInput",
                  "x": 0,
                  "y": 0,
                  "measuredW": 140,
                  "measuredH": 30,
                  "properties": {
                    "text": "Architecture",
                    "size": 13,
                    "color": 16777215,
                    "borderColor": 8867582,
                    "backgroundAlpha": 1
                  }
                }
              ]
            }
          }
        },
        {
          "typeID": "__group__",
          "x": 170,
          "y": 300,
          "measuredW": 140,
          "measuredH": 30,
          "properties": {
            "controlName": "sequences@sequences"
          },
          "children": {
            "controls": {
              "control": [
                {
                  "typeID": "TextInput",
                  "x": 0,
                  "y": 0,
                  "measuredW": 140,
                  "measuredH": 30,
                  "properties": {
                    "text": "Sequences",
                    "size": 13,
                    "color": 16777215,
                    "borderColor": 8867582,
                    "backgroundAlpha": 1
                  }
                }
              ]
            }
          }
        },
        {
          "typeID": "__group__",
          "x": 320,
          "y": 300,
          "measuredW": 140,
          "measuredH": 30,
          "properties": {
            "controlName": "scoreboards@scoreboards"
          },
          "children": {
            "controls": {
              "control": [
                {
                  "typeID": "TextInput",
                  "x": 0,
                  "y": 0,
                  "measuredW": 140,
                  "measuredH": 30,
                  "properties": {
                    "text": "Scoreboards",
                    "size": 13,
                    "color": 16777215,
                    "borderColor": 8867582,
                    "backgroundAlpha": 1
                  }
                }
              ]
            }
          }
        },
        {
          "typeID": "__group__",
          "x": 470,
          "y": 300,
          "measuredW": 140,
          "measuredH": 30,
          "properties": {
            "controlName": "ral@ral"
          },
          "children": {
            "controls": {
              "control": [
                {
                  "typeID": "TextInput",
                  "x": 0,
                  "y": 0,
                  "measuredW": 140,
                  "measuredH": 30,
                  "properties": {
                    "text": "RAL",
                    "size": 13,
                    "color": 16777215,
                    "borderColor": 8867582,
                    "backgroundAlpha": 1
                  }
                }
              ]
            }
          }
        },
        {
          "typeID": "Canvas",
          "x": 10,
          "y": 360,
          "measuredW": 780,
          "measuredH": 80,
          "properties": {
            "color": 16317180,
            "borderColor": 14870768,
            "backgroundAlpha": 0.5
          }
        },
        {
          "typeID": "TextInput",
          "x": 20,
          "y": 370,
          "measuredW": 760,
          "measuredH": 25,
          "properties": {
            "text": "Advanced",
            "size": 15,
            "bold": true,
            "color": 14973201,
            "borderColor": 14973201,
            "textColor": 16777215
          }
        },
        {
          "typeID": "__group__",
          "x": 20,
          "y": 400,
          "measuredW": 140,
          "measuredH": 30,
          "properties": {
            "controlName": "formal-verification@formal-verification"
          },
          "children": {
            "controls": {
              "control": [
                {
                  "typeID": "TextInput",
                  "x": 0,
                  "y": 0,
                  "measuredW": 140,
                  "measuredH": 30,
                  "properties": {
                    "text": "Formal Verification",
                    "size": 13,
                    "color": 16777215,
                    "borderColor": 14973201,
                    "backgroundAlpha": 1
                  }
                }
              ]
            }
          }
        },
        {
          "typeID": "__group__",
          "x": 170,
          "y": 400,
          "measuredW": 140,
          "measuredH": 30,
          "properties": {
            "controlName": "emulation@emulation"
          },
          "children": {
            "controls": {
              "control": [
                {
                  "typeID": "TextInput",
                  "x": 0,
                  "y": 0,
                  "measuredW": 140,
                  "measuredH": 30,
                  "properties": {
                    "text": "Emulation",
                    "size": 13,
                    "color": 16777215,
                    "borderColor": 14973201,
                    "backgroundAlpha": 1
                  }
                }
              ]
            }
          }
        },
        {
          "typeID": "__group__",
          "x": 320,
          "y": 400,
          "measuredW": 140,
          "measuredH": 30,
          "properties": {
            "controlName": "performance-dv@performance-dv"
          },
          "children": {
            "controls": {
              "control": [
                {
                  "typeID": "TextInput",
                  "x": 0,
                  "y": 0,
                  "measuredW": 140,
                  "measuredH": 30,
                  "properties": {
                    "text": "Performance DV",
                    "size": 13,
                    "color": 16777215,
                    "borderColor": 14973201,
                    "backgroundAlpha": 1
                  }
                }
              ]
            }
          }
        },
        {
          "typeID": "__group__",
          "x": 470,
          "y": 400,
          "measuredW": 140,
          "measuredH": 30,
          "properties": {
            "controlName": "gate-sims@gate-sims"
          },
          "children": {
            "controls": {
              "control": [
                {
                  "typeID": "TextInput",
                  "x": 0,
                  "y": 0,
                  "measuredW": 140,
                  "measuredH": 30,
                  "properties": {
                    "text": "Gate Sims",
                    "size": 13,
                    "color": 16777215,
                    "borderColor": 14973201,
                    "backgroundAlpha": 1
                  }
                }
              ]
            }
          }
        },
        {
          "typeID": "Canvas",
          "x": 10,
          "y": 460,
          "measuredW": 780,
          "measuredH": 80,
          "properties": {
            "color": 16317180,
            "borderColor": 14870768,
            "backgroundAlpha": 0.5
          }
        },
        {
          "typeID": "TextInput",
          "x": 20,
          "y": 470,
          "measuredW": 760,
          "measuredH": 25,
          "properties": {
            "text": "Career",
            "size": 15,
            "bold": true,
            "color": 1013358,
            "borderColor": 1013358,
            "textColor": 16777215
          }
        },
        {
          "typeID": "__group__",
          "x": 20,
          "y": 500,
          "measuredW": 140,
          "measuredH": 30,
          "properties": {
            "controlName": "verification-lead@verification-lead"
          },
          "children": {
            "controls": {
              "control": [
                {
                  "typeID": "TextInput",
                  "x": 0,
                  "y": 0,
                  "measuredW": 140,
                  "measuredH": 30,
                  "properties": {
                    "text": "Verification Lead",
                    "size": 13,
                    "color": 16777215,
                    "borderColor": 1013358,
                    "backgroundAlpha": 1
                  }
                }
              ]
            }
          }
        },
        {
          "typeID": "__group__",
          "x": 170,
          "y": 500,
          "measuredW": 140,
          "measuredH": 30,
          "properties": {
            "controlName": "methodology@methodology"
          },
          "children": {
            "controls": {
              "control": [
                {
                  "typeID": "TextInput",
                  "x": 0,
                  "y": 0,
                  "measuredW": 140,
                  "measuredH": 30,
                  "properties": {
                    "text": "Methodology",
                    "size": 13,
                    "color": 16777215,
                    "borderColor": 1013358,
                    "backgroundAlpha": 1
                  }
                }
              ]
            }
          }
        },
        {
          "typeID": "__group__",
          "x": 320,
          "y": 500,
          "measuredW": 140,
          "measuredH": 30,
          "properties": {
            "controlName": "mentoring@mentoring"
          },
          "children": {
            "controls": {
              "control": [
                {
                  "typeID": "TextInput",
                  "x": 0,
                  "y": 0,
                  "measuredW": 140,
                  "measuredH": 30,
                  "properties": {
                    "text": "Mentoring",
                    "size": 13,
                    "color": 16777215,
                    "borderColor": 1013358,
                    "backgroundAlpha": 1
                  }
                }
              ]
            }
          }
        },
        {
          "typeID": "__group__",
          "x": 470,
          "y": 500,
          "measuredW": 140,
          "measuredH": 30,
          "properties": {
            "controlName": "director@director"
          },
          "children": {
            "controls": {
              "control": [
                {
                  "typeID": "TextInput",
                  "x": 0,
                  "y": 0,
                  "measuredW": 140,
                  "measuredH": 30,
                  "properties": {
                    "text": "Director",
                    "size": 13,
                    "color": 16777215,
                    "borderColor": 1013358,
                    "backgroundAlpha": 1
                  }
                }
              ]
            }
          }
        }
      ]
    },
    "measuredW": 800,
    "measuredH": 560
  }
}